gen/__init__.py
gen/gen.cpython-313-darwin.so
gen-0.1.22.dist-info/METADATA
gen-0.1.22.dist-info/WHEEL
gen-0.1.22.dist-info/licenses/LICENSE
gen-0.1.22.dist-info/RECORD
