Metadata-Version: 2.4
Name: gen
Version: 0.1.22
Classifier: Programming Language :: Rust
Classifier: Programming Language :: Python :: Implementation :: CPython
Classifier: Programming Language :: Python :: 3.8
Classifier: Programming Language :: Python :: 3.9
Classifier: Programming Language :: Python :: 3.10
Classifier: Programming Language :: Python :: 3.11
Classifier: Programming Language :: Python :: 3.12
License-File: LICENSE
Summary: Python bindings for the Gen graph database
Home-Page: https://genhub.bio
Requires-Python: >=3.8
